pyodata/__init__.py
pyodata/client.py
pyodata/exceptions.py
pyodata/v2/__init__.py
pyodata/v2/model.py
pyodata/v2/service.py
pyodata/vendor/SAP.py
pyodata/vendor/__init__.py
tests/__init__.py
tests/conftest.py
tests/test_model_v2.py
tests/test_model_v2_EdmStructTypeSerializer.py
tests/test_model_v2_VariableDeclaration.py
tests/test_service_v2.py
tests/test_vendor_microsoft.py
tests/test_vendor_sap.py
pyodata-1.11.1.dist-info/LICENSE
pyodata-1.11.1.dist-info/METADATA
pyodata-1.11.1.dist-info/WHEEL
pyodata-1.11.1.dist-info/top_level.txt
pyodata-1.11.1.dist-info/RECORD
