Metadata-Version: 2.1
Name: pyodata
Version: 1.11.1
Summary: Enterprise ready Python OData client
Home-page: https://github.com/SAP/python-pyodata
Author: Jakub Filak, Michal Nezerka, Patrik Petrik, Petr Hanak
Author-email: jakub.filak@sap.com, michal.nezerka@sap.com, patrik.petrik@sap.com, petr.hanak@sap.com
License: Apache License Version 2.0
Classifier: Development Status :: 5 - Production/Stable
Classifier: Environment :: Web Environment
Classifier: Intended Audience :: Developers
Classifier: License :: OSI Approved :: Apache Software License
Classifier: Operating System :: OS Independent
Classifier: Programming Language :: Python :: 3.7
Classifier: Programming Language :: Python :: 3.8
Classifier: Programming Language :: Python :: 3.9
Classifier: Programming Language :: Python :: 3.10
Classifier: Topic :: Internet :: WWW/HTTP
Classifier: Topic :: Software Development
Classifier: Topic :: Software Development :: Libraries :: Python Modules
License-File: LICENSE
Requires-Dist: lxml >=4.1.1
